pyramid_grpc/__init__.py
pyramid_grpc/decorators.py
pyramid_grpc/interseptors/__init__.py
pyramid_grpc/interseptors/request.py
pyramid_grpc/interseptors/transaction.py
pyramid_grpc/main.py
pyramid_grpc-0.0.9.dist-info/LICENSE
pyramid_grpc-0.0.9.dist-info/METADATA
pyramid_grpc-0.0.9.dist-info/WHEEL
pyramid_grpc-0.0.9.dist-info/entry_points.txt
pyramid_grpc-0.0.9.dist-info/RECORD
