Metadata-Version: 2.1
Name: pyramid_grpc
Version: 0.0.9
Summary: Grpc with pyramid
Home-page: https://github.com/tomas_correa/pyramid-grpc
Author: Tomas Correa
Author-email: ftomas.correa@gmail.com
Requires-Python: >=3.8,<4.0
Classifier: Programming Language :: Python :: 3
Classifier: Programming Language :: Python :: 3.8
Classifier: Programming Language :: Python :: 3.9
Classifier: Programming Language :: Python :: 3.10
Classifier: Programming Language :: Python :: 3.11
Classifier: Programming Language :: Python :: 3.12
Requires-Dist: click
Requires-Dist: grpc-interceptor
Requires-Dist: grpcio
Requires-Dist: grpcio-reflection (>=1.58.0,<2.0.0)
Requires-Dist: pyramid
Project-URL: Documentation, https://tomas_correa.github.io/pyramid-grpc/
Project-URL: Repository, https://github.com/tomas_correa/pyramid-grpc
